giphon/__about__.py
giphon/__init__.py
giphon/__main__.py
giphon/envvars.py
giphon/git.py
giphon/gitlab.py
giphon/siphon.py
giphon-0.2.0.dist-info/METADATA
giphon-0.2.0.dist-info/WHEEL
giphon-0.2.0.dist-info/entry_points.txt
giphon-0.2.0.dist-info/licenses/LICENSE
giphon-0.2.0.dist-info/RECORD
