Metadata-Version: 2.3
Name: giphon
Version: 0.2.0
Summary: Copy locally a Gitlab group or instance
Project-URL: Bug Reports, https://github.com/kabooboo/giphon/issues
Project-URL: Documentation, https://github.com/kabooboo/giphon
Project-URL: Homepage, https://github.com/kabooboo/giphon
Project-URL: Source Code, https://github.com/kabooboo/giphon
Author-email: Gabriel Creti <gabrielcreti@gmail.com>
License-File: LICENSE
Keywords: clone,copy,gitlab
Classifier: Development Status :: 5 - Production/Stable
Classifier: Intended Audience :: Developers
Classifier: License :: OSI Approved :: Apache Software License
Classifier: Operating System :: OS Independent
Classifier: Programming Language :: Python :: 3
Classifier: Programming Language :: Python :: 3 :: Only
Classifier: Programming Language :: Python :: 3.7
Classifier: Programming Language :: Python :: 3.8
Classifier: Programming Language :: Python :: 3.9
Classifier: Programming Language :: Python :: 3.10
Classifier: Programming Language :: Python :: 3.11
Classifier: Topic :: Software Development :: Build Tools
Requires-Python: >=3.7
Requires-Dist: gitpython<4,>=3
Requires-Dist: python-gitlab<5,>=3
Requires-Dist: rich<14,>=12
Requires-Dist: typer>=0.7
Provides-Extra: test
Requires-Dist: pytest; extra == 'test'
